bi_code/__init__.py
bi_code-0.5.dist-info/METADATA
bi_code-0.5.dist-info/WHEEL
bi_code-0.5.dist-info/top_level.txt
bi_code-0.5.dist-info/RECORD
