Metadata-Version: 2.4
Name: bi_code
Version: 0.5
Summary: BI codes for Bsc it sem 6
Home-page: https://github.com/yourusername/mypackage
Author: Mia Khalifa
Author-email: khalifa@gmail.com
Classifier: Programming Language :: Python :: 3
Classifier: License :: OSI Approved :: MIT License
Classifier: Operating System :: OS Independent
Requires-Python: >=3.6
Dynamic: author
Dynamic: author-email
Dynamic: classifier
Dynamic: description
Dynamic: description-content-type
Dynamic: home-page
Dynamic: requires-python
Dynamic: summary
